seleniumlibraries/__init__.py
seleniumlibraries/browser.py
seleniumlibraries/element.py
seleniumlibraries/page.py
seleniumlibraries/py.typed
seleniumlibraries-0.2.0.dist-info/licenses/LICENSE
seleniumlibraries-0.2.0.dist-info/METADATA
seleniumlibraries-0.2.0.dist-info/WHEEL
seleniumlibraries-0.2.0.dist-info/top_level.txt
seleniumlibraries-0.2.0.dist-info/RECORD
