Metadata-Version: 2.4
Name: seleniumlibraries
Version: 0.2.0
Summary: The Selenium libraries to reduce codes for Python.
Author-email: Yukihiko Shinoda <yuk.hik.future@gmail.com>
Maintainer-email: Yukihiko Shinoda <yuk.hik.future@gmail.com>
License: MIT License
Project-URL: homepage, https://github.com/yukihiko-shinoda/selenium-libraries
Project-URL: repository, https://github.com/yukihiko-shinoda/selenium-libraries
Keywords: selenium,scraping
Classifier: Development Status :: 4 - Beta
Classifier: Intended Audience :: Developers
Classifier: License :: OSI Approved :: MIT License
Classifier: Natural Language :: English
Classifier: Operating System :: POSIX :: Linux
Classifier: Programming Language :: Python
Classifier: Programming Language :: Python :: 3
Classifier: Programming Language :: Python :: 3.7
Classifier: Programming Language :: Python :: 3.8
Classifier: Programming Language :: Python :: 3.9
Classifier: Programming Language :: Python :: 3.10
Classifier: Programming Language :: Python :: 3.11
Classifier: Programming Language :: Python :: 3.12
Classifier: Programming Language :: Python :: 3.13
Classifier: Topic :: Internet :: WWW/HTTP
Classifier: Topic :: Internet :: WWW/HTTP :: Browsers
Classifier: Topic :: Software Development
Classifier: Topic :: Software Development :: Libraries
Classifier: Topic :: Software Development :: Libraries :: Python Modules
Classifier: Topic :: Utilities
Classifier: Typing :: Typed
Requires-Python: >=3.7
License-File: LICENSE
Requires-Dist: selenium
Dynamic: license-file
